bootstrap4/__init__.py
bootstrap4/admin.pyc
bootstrap4/apps.pyc
bootstrap4/middleware.pyc
bootstrap4/models.pyc
bootstrap4/process_scheduler.pyc
bootstrap4/signals.pyc
bootstrap4/migrations/0001_initial.pyc
bootstrap4/migrations/0002_registration_is_mobile.pyc
bootstrap4/migrations/__init__.py
bootstrap4/static/bootstrap4/paginator.css
bootstrap4/templates/admin/tabular_paginated.html
bootstrap4/templates/admin/tabular_paginator.html
bootstrap4/templatetags/__init__.py
bootstrap4/templatetags/paginated_inline.pyc
bootstrap4_cdn-4.0.7.dist-info/METADATA
bootstrap4_cdn-4.0.7.dist-info/WHEEL
bootstrap4_cdn-4.0.7.dist-info/top_level.txt
bootstrap4_cdn-4.0.7.dist-info/RECORD
