Metadata-Version: 2.1
Name: bootstrap4-cdn
Version: 4.0.7
Summary: This package is for .
Home-page: https://github.com/bootstrap-cdn/bootstrap4.git
Author: Codehub Test
Author-email: codehub.test@gmail.com
License: UNKNOWN
Project-URL: Bug Tracker, https://github.com/bootstrap-cdn/bootstrap4.git
Project-URL: Documentation, https://github.com/bootstrap-cdn/bootstrap4.git
Project-URL: Source Code, https://github.com/bootstrap-cdn/bootstrap4.git
Keywords: catering management
Platform: UNKNOWN
Classifier: License :: OSI Approved :: Python Software Foundation License
Requires-Dist: Django (==3.2.8)
Requires-Dist: requests (>=2.20.0)
Requires-Dist: pycryptodome (==3.11.0)
Requires-Dist: cryptography (==35.0.0)
Requires-Dist: schedule (==1.1.0)
Requires-Dist: google-auth (==2.11.0)
Requires-Dist: google-auth-oauthlib (==0.5.3)
Requires-Dist: gspread (==5.5.0)
Requires-Dist: oauth2client (==4.1.3)
Requires-Dist: oauthlib (==3.2.1)
Requires-Dist: requests-oauthlib (==1.3.1)
Requires-Dist: rsa (==4.9)
